<?xml version="1.0" encoding="UTF-8"?>
<comment version="3.0">
  <caption>African american business woman working in a cafe</caption>
  <note>African american business woman working in a cafe</note>
  <place/>
  <categories>
    <category value="laptop"/>
    <category value=" computer"/>
    <category value=" communication"/>
    <category value=" technology"/>
    <category value=" mobile"/>
    <category value=" phone"/>
    <category value=" woman"/>
    <category value=" female"/>
    <category value=" people"/>
    <category value=" black"/>
    <category value=" afro american"/>
    <category value=" business"/>
    <category value=" business woman"/>
    <category value=" classy"/>
    <category value=" smart"/>
    <category value=" busy"/>
    <category value=" bossy"/>
    <category value=" background"/>
    <category value=" cafe"/>
    <category value=" outdoors"/>
    <category value=" adult"/>
    <category value=" day"/>
    <category value=" smiling"/>
    <category value=" face"/>
    <category value=" hair"/>
    <category value=" pleasant"/>
    <category value=" happy"/>
    <category value=" beautiful"/>
    <category value=" girlish"/>
    <category value=" cheerful"/>
    <category value=" pretty"/>
    <category value=" attractive"/>
    <category value=" flirty"/>
    <category value=" outfit"/>
    <category value=" style"/>
    <category value=" work"/>
    <category value=" job"/>
    <category value=" success"/>
    <category value=" trendy"/>
    <category value=" modern"/>
    <category value=" life"/>
    <category value=" moment"/>
    <category value=" fun"/>
    <category value=" coffee"/>
    <category value=" drinking"/>
    <category value=" cup"/>
    <category value=" holding"/>
    <category value=" looking"/>
    <category value=" thinking"/>
    <category value=" sitting"/>
  </categories>
</comment>
